{
  "quote": "Hold the vision, trust the process.",
  "author": "",
  "week": "4",
  "date": "2026-01-31",
  "video_url": "",
  "past_quotes": [
    {
      "quote": "Make it happen.",
      "author": "",
      "week": "3",
      "date": "2025-10-15",
      "video_url": ""
    },
    {
      "quote": "Move with intention.",
      "author": "",
      "week": "2",
      "date": "2025-09-22",
      "video_url": ""
    },
    {
      "quote": "Create the things you wish existed.",
      "author": "",
      "week": "1",
      "date": "2025-09-14",
      "video_url": ""
    }
  ]
}
